COPYING.txt
MANIFEST.in
setup.py
PyPhyloGenomics.egg-info/PKG-INFO
PyPhyloGenomics.egg-info/SOURCES.txt
PyPhyloGenomics.egg-info/dependency_links.txt
PyPhyloGenomics.egg-info/requires.txt
PyPhyloGenomics.egg-info/top_level.txt
doc/Makefile
doc/conf.py
doc/favicon.ico
doc/getting-started.rst
doc/index.rst
doc/make.bat
doc/ngs_analysis.rst
doc/_build/doctrees/environment.pickle
doc/_build/doctrees/getting-started.doctree
doc/_build/doctrees/index.doctree
doc/_build/doctrees/ngs_analysis.doctree
doc/_build/html/.buildinfo
doc/_build/html/genindex.html
doc/_build/html/getting-started.html
doc/_build/html/index.html
doc/_build/html/ngs_analysis.html
doc/_build/html/objects.inv
doc/_build/html/py-modindex.html
doc/_build/html/search.html
doc/_build/html/searchindex.js
doc/_build/html/_sources/getting-started.txt
doc/_build/html/_sources/index.txt
doc/_build/html/_sources/ngs_analysis.txt
doc/_build/html/_static/ajax-loader.gif
doc/_build/html/_static/basic.css
doc/_build/html/_static/comment-bright.png
doc/_build/html/_static/comment-close.png
doc/_build/html/_static/comment.png
doc/_build/html/_static/doctools.js
doc/_build/html/_static/down-pressed.png
doc/_build/html/_static/down.png
doc/_build/html/_static/favicon.ico
doc/_build/html/_static/file.png
doc/_build/html/_static/jquery.js
doc/_build/html/_static/minus.png
doc/_build/html/_static/nature.css
doc/_build/html/_static/plus.png
doc/_build/html/_static/pygments.css
doc/_build/html/_static/searchtools.js
doc/_build/html/_static/underscore.js
doc/_build/html/_static/up-pressed.png
doc/_build/html/_static/up.png
doc/_build/html/_static/websupport.js
pyphylogenomics/BLAST.py
pyphylogenomics/MUSCLE.py
pyphylogenomics/NGS.py
pyphylogenomics/OrthoDB.py
pyphylogenomics/__init__.py