Metadata-Version: 1.1
Name: PyPhyloGenomics
Version: 0.3.1
Summary: Tools to work in phylogenomics, from NSG group http://nymphalidae.utu.fi
Home-page: http://carlosp420.github.com/PyPhyloGenomics/
Author: Carlos Pena, Victor Solis, Pavel Matos, Chris Wheat
Author-email: mycalesis@gmail.com
License: GPL v3
Download-URL: http://carlosp420.github.com/PyPhyloGenomics/
Keywords: DNA,genomics,genomes,phylogenetics,genes
Platform: UNKNOWN
Classifier: Programming Language :: Python
Classifier: Topic :: Scientific/Engineering :: Bio-Informatics
Classifier: Intended Audience :: Science/Research
Classifier: License :: OSI Approved :: GNU General Public License v2 (GPLv2)
Classifier: Operating System :: OS Independent
Classifier: Environment :: Console
